{
  "schema": "polygram.rung5_rank_verification.v1",
  "runs": {
    "rung5_k2_seed0": {
      "k": 2,
      "cap": 32,
      "seed": 0,
      "rows": [
        {
          "n": 8,
          "rank_1e_12": 8,
          "rank_1e_9": 8,
          "rank_1e_6": 8,
          "sigma_max": 1.4459514197872456,
          "sigma_min_nonzero": 0.49647756204960297,
          "sigma_min": 0.49647756204960297
        },
        {
          "n": 16,
          "rank_1e_12": 16,
          "rank_1e_9": 16,
          "rank_1e_6": 16,
          "sigma_max": 2.303027564276678,
          "sigma_min_nonzero": 0.15094252207645686,
          "sigma_min": 0.15094252207645686
        },
        {
          "n": 32,
          "rank_1e_12": 32,
          "rank_1e_9": 32,
          "rank_1e_6": 32,
          "sigma_max": 2.9870138990711257,
          "sigma_min_nonzero": 0.00280209873348778,
          "sigma_min": 0.00280209873348778
        },
        {
          "n": 64,
          "rank_1e_12": 32,
          "rank_1e_9": 32,
          "rank_1e_6": 32,
          "sigma_max": 5.024823596346684,
          "sigma_min_nonzero": 1.0204446104106234e-15,
          "sigma_min": 7.013271617121573e-18
        }
      ]
    },
    "rung5_k2_seed42": {
      "k": 2,
      "cap": 32,
      "seed": 42,
      "rows": [
        {
          "n": 8,
          "rank_1e_12": 8,
          "rank_1e_9": 8,
          "rank_1e_6": 8,
          "sigma_max": 1.4524769949699365,
          "sigma_min_nonzero": 0.500600850474269,
          "sigma_min": 0.500600850474269
        },
        {
          "n": 16,
          "rank_1e_12": 16,
          "rank_1e_9": 16,
          "rank_1e_6": 16,
          "sigma_max": 2.397200683549854,
          "sigma_min_nonzero": 0.1006502986840113,
          "sigma_min": 0.1006502986840113
        },
        {
          "n": 32,
          "rank_1e_12": 32,
          "rank_1e_9": 32,
          "rank_1e_6": 32,
          "sigma_max": 3.347790022912803,
          "sigma_min_nonzero": 0.0018000245797463754,
          "sigma_min": 0.0018000245797463754
        },
        {
          "n": 64,
          "rank_1e_12": 32,
          "rank_1e_9": 32,
          "rank_1e_6": 32,
          "sigma_max": 5.366725762273612,
          "sigma_min_nonzero": 0.21568835557645888,
          "sigma_min": 1.583068614831145e-17
        }
      ]
    },
    "rung5_k3_seed0": {
      "k": 3,
      "cap": 64,
      "seed": 0,
      "rows": [
        {
          "n": 16,
          "rank_1e_12": 16,
          "rank_1e_9": 16,
          "rank_1e_6": 16,
          "sigma_max": 1.9082026834295718,
          "sigma_min_nonzero": 0.29816418505889714,
          "sigma_min": 0.29816418505889714
        },
        {
          "n": 32,
          "rank_1e_12": 32,
          "rank_1e_9": 32,
          "rank_1e_6": 32,
          "sigma_max": 3.0285480305231656,
          "sigma_min_nonzero": 0.07746619784169383,
          "sigma_min": 0.07746619784169383
        },
        {
          "n": 64,
          "rank_1e_12": 64,
          "rank_1e_9": 64,
          "rank_1e_6": 64,
          "sigma_max": 3.7534745989115703,
          "sigma_min_nonzero": 0.0004327772836109872,
          "sigma_min": 0.0004327772836109872
        },
        {
          "n": 128,
          "rank_1e_12": 64,
          "rank_1e_9": 64,
          "rank_1e_6": 64,
          "sigma_max": 5.960478797282449,
          "sigma_min_nonzero": 1.033684847605096e-15,
          "sigma_min": 4.747307562550665e-18
        }
      ]
    },
    "rung5_k3_seed42": {
      "k": 3,
      "cap": 64,
      "seed": 42,
      "rows": [
        {
          "n": 16,
          "rank_1e_12": 16,
          "rank_1e_9": 16,
          "rank_1e_6": 16,
          "sigma_max": 1.7695436987741828,
          "sigma_min_nonzero": 0.3304689250322225,
          "sigma_min": 0.3304689250322225
        },
        {
          "n": 32,
          "rank_1e_12": 32,
          "rank_1e_9": 32,
          "rank_1e_6": 32,
          "sigma_max": 2.283703613070114,
          "sigma_min_nonzero": 0.0985729653557884,
          "sigma_min": 0.0985729653557884
        },
        {
          "n": 64,
          "rank_1e_12": 64,
          "rank_1e_9": 64,
          "rank_1e_6": 64,
          "sigma_max": 3.493967953995069,
          "sigma_min_nonzero": 0.000276064313294023,
          "sigma_min": 0.000276064313294023
        },
        {
          "n": 128,
          "rank_1e_12": 64,
          "rank_1e_9": 64,
          "rank_1e_6": 64,
          "sigma_max": 5.1740959391413375,
          "sigma_min_nonzero": 1.0313187810285304e-15,
          "sigma_min": 1.3761761373954234e-17
        }
      ]
    },
    "rung5_k4_seed0": {
      "k": 4,
      "cap": 128,
      "seed": 0,
      "rows": [
        {
          "n": 32,
          "rank_1e_12": 32,
          "rank_1e_9": 32,
          "rank_1e_6": 32,
          "sigma_max": 1.9750250314153757,
          "sigma_min_nonzero": 0.2991237685567953,
          "sigma_min": 0.2991237685567953
        },
        {
          "n": 64,
          "rank_1e_12": 64,
          "rank_1e_9": 64,
          "rank_1e_6": 64,
          "sigma_max": 2.733018707858957,
          "sigma_min_nonzero": 0.09174276864982658,
          "sigma_min": 0.09174276864982658
        },
        {
          "n": 128,
          "rank_1e_12": 128,
          "rank_1e_9": 128,
          "rank_1e_6": 128,
          "sigma_max": 3.7770395849048275,
          "sigma_min_nonzero": 3.170144129178815e-05,
          "sigma_min": 3.170144129178815e-05
        },
        {
          "n": 256,
          "rank_1e_12": 128,
          "rank_1e_9": 128,
          "rank_1e_6": 128,
          "sigma_max": 5.411794383225064,
          "sigma_min_nonzero": 1.0057230755355201e-15,
          "sigma_min": 1.4042942533039484e-18
        }
      ]
    },
    "rung5_k4_seed42": {
      "k": 4,
      "cap": 128,
      "seed": 42,
      "rows": [
        {
          "n": 32,
          "rank_1e_12": 32,
          "rank_1e_9": 32,
          "rank_1e_6": 32,
          "sigma_max": 2.3642094200751287,
          "sigma_min_nonzero": 0.18726249397794545,
          "sigma_min": 0.18726249397794545
        },
        {
          "n": 64,
          "rank_1e_12": 64,
          "rank_1e_9": 64,
          "rank_1e_6": 64,
          "sigma_max": 2.8731077455009584,
          "sigma_min_nonzero": 0.10875938636485001,
          "sigma_min": 0.10875938636485001
        },
        {
          "n": 128,
          "rank_1e_12": 128,
          "rank_1e_9": 128,
          "rank_1e_6": 128,
          "sigma_max": 4.071057383707208,
          "sigma_min_nonzero": 2.6620545218786496e-05,
          "sigma_min": 2.6620545218786496e-05
        },
        {
          "n": 256,
          "rank_1e_12": 128,
          "rank_1e_9": 128,
          "rank_1e_6": 128,
          "sigma_max": 5.598842671804736,
          "sigma_min_nonzero": 1.0025113239350444e-15,
          "sigma_min": 4.7904530015133086e-18
        }
      ]
    }
  }
}